corenlp_webclient/__init__.py
corenlp_webclient/annotators.py
corenlp_webclient/client.py
corenlp_webclient/helpers.py
corenlp_webclient/options.py
corenlp_webclient/version.py
corenlp_webclient-0.1a3.dist-info/LICENSE.txt
corenlp_webclient-0.1a3.dist-info/METADATA
corenlp_webclient-0.1a3.dist-info/WHEEL
corenlp_webclient-0.1a3.dist-info/top_level.txt
corenlp_webclient-0.1a3.dist-info/RECORD
